[
    {
        "name": "id",
        "dbType": "string,11",
        "htmlType": "text",
        "validations": null,
        "searchable": false,
        "fillable": false,
        "primary": true,
        "inForm": false,
        "inIndex": false,
        "inView": false
    },
    {
        "name": "registration",
        "dbType": "datetime",
        "htmlType": "date",
        "validations": "required",
        "searchable": true,
        "fillable": true,
        "primary": false,
        "inForm": true,
        "inIndex": true,
        "inView": true
    },
    {
        "name": "name",
        "dbType": "string,100",
        "htmlType": "text",
        "validations": "required|string|max:100|string|max:100",
        "searchable": true,
        "fillable": true,
        "primary": false,
        "inForm": true,
        "inIndex": true,
        "inView": true
    },
    {
        "name": "surname",
        "dbType": "string,100",
        "htmlType": "text",
        "validations": "required|string|max:100|string|max:100",
        "searchable": true,
        "fillable": true,
        "primary": false,
        "inForm": true,
        "inIndex": true,
        "inView": true
    },
    {
        "name": "birthday",
        "dbType": "date",
        "htmlType": "date",
        "validations": "required",
        "searchable": true,
        "fillable": true,
        "primary": false,
        "inForm": true,
        "inIndex": true,
        "inView": true
    },
    {
        "name": "phone",
        "dbType": "string,20:nullable",
        "htmlType": "text",
        "validations": "nullable|string|max:20|nullable|string|max:20",
        "searchable": true,
        "fillable": true,
        "primary": false,
        "inForm": true,
        "inIndex": true,
        "inView": true
    },
    {
        "name": "email",
        "dbType": "string,254:nullable",
        "htmlType": "text",
        "validations": "nullable|string|max:254|nullable|string|max:254",
        "searchable": true,
        "fillable": true,
        "primary": false,
        "inForm": true,
        "inIndex": true,
        "inView": true
    },
    {
        "name": "address",
        "dbType": "string,500",
        "htmlType": "text",
        "validations": "required|string|max:500|string|max:500",
        "searchable": true,
        "fillable": true,
        "primary": false,
        "inForm": true,
        "inIndex": true,
        "inView": true
    },
    {
        "name": "experience",
        "dbType": "integer,false",
        "htmlType": null,
        "validations": "required|integer|integer",
        "searchable": true,
        "fillable": true,
        "primary": false,
        "inForm": true,
        "inIndex": true,
        "inView": true
    },
    {
        "type": "relation",
        "relation": "1tm,Farm,owner_id"
    },
    {
        "type": "relation",
        "relation": "1tm,Cooperative,founder_id"
    },
    {
        "type": "relation",
        "relation": "1tm,Cooperative,president_id"
    },
    {
        "type": "relation",
        "relation": "mtm,Cooperative,cooperativemember"
    }
]
